notty/__init__.py
notty/__main__.py
notty/app.py
notty/lib/__init__.py
notty/lib/CommandAliases.py
notty/lib/ConfirmationDialog.py
notty/lib/db.py
notty/lib/MessageDialog.py
notty/lib/TextInputDialog.py
notty/screens/__init__.py
notty/screens/create.py
notty/screens/list.py
notty/utils/__init__.py
notty/utils/date_now.py
notty/utils/if_mousedown.py
notty-1.3.7.dist-info/entry_points.txt
notty-1.3.7.dist-info/WHEEL
notty-1.3.7.dist-info/METADATA
notty-1.3.7.dist-info/RECORD
