Metadata-Version: 2.1
Name: notty
Version: 1.3.7
Summary: 📝⚡ Fast terminal-based notes application
Home-page: https://github.com/jarvis394/notty
License: MIT
Keywords: notes,quick,console,terminal,app,pip
Author: jarvis394
Author-email: tarnatovski@gmail.com
Requires-Python: >=3.7,<4.0
Classifier: License :: OSI Approved :: MIT License
Classifier: Programming Language :: Python :: 3
Classifier: Programming Language :: Python :: 3.7
Classifier: Programming Language :: Python :: 3.8
Requires-Dist: appdirs (>=1.4.3,<2.0.0)
Requires-Dist: click (>=7.0,<8.0)
Requires-Dist: colorama (>=0.4.3,<0.5.0)
Requires-Dist: prompt_toolkit (>=3.0.3,<4.0.0)
Project-URL: Bug Tracker, https://github.com/jarvis394/notty/issues
Project-URL: Repository, https://github.com/jarvis394/notty
